ccformat.py
ccfind-1.1.1.dist-info/METADATA
ccfind-1.1.1.dist-info/WHEEL
ccfind-1.1.1.dist-info/top_level.txt
ccfind-1.1.1.dist-info/RECORD
