Metadata-Version: 2.1
Name: ccfind
Version: 1.1.1
Summary: CC Formatter For Checker Bots
Home-page: UNKNOWN
Author: doesntexit
Author-email: edwinhamal@gmail.com
License: UNKNOWN
Platform: UNKNOWN
Requires-Python: >=3.6
